lib_ftep/__init__.py
lib_ftep/ftp.py
lib_ftep-1.1.1.dist-info/METADATA
lib_ftep-1.1.1.dist-info/WHEEL
lib_ftep-1.1.1.dist-info/RECORD
