Metadata-Version: 2.3
Name: lib-ftep
Version: 1.1.1
Summary: 
Author: Nathan Blum
Author-email: n.blum@student.tudelft.nl
Requires-Python: >=3.10
Classifier: Programming Language :: Python :: 3
Classifier: Programming Language :: Python :: 3.10
Classifier: Programming Language :: Python :: 3.11
Classifier: Programming Language :: Python :: 3.12
Classifier: Programming Language :: Python :: 3.13
Requires-Dist: lib-idoc (>=0.1.1,<0.2.0)
Requires-Dist: lib-invoice (>=0.1.1,<0.2.0)
